<?xml version="1.1" encoding="UTF-8" standalone="no"?>
<databaseChangeLog
	xmlns="http://www.liquibase.org/xml/ns/dbchangelog"
	xmlns:ext="http://www.liquibase.org/xml/ns/dbchangelog-ext"
	xmlns:xsi="http://www.w3.org/2001/XMLSchema-instance"
	xsi:schemaLocation="http://www.liquibase.org/xml/ns/dbchangelog-ext http://www.liquibase.org/xml/ns/dbchangelog/dbchangelog-ext.xsd http://www.liquibase.org/xml/ns/dbchangelog http://www.liquibase.org/xml/ns/dbchangelog/dbchangelog-3.5.xsd">

    <!-- DEPARTURE -->
    
    <changeSet author="FLH" id="ass-airport-assistance-data-1">
    
    	<insert tableName="ass_departure">
            <column name="id" value="57iZ7hEtMLx2IpKg0x6MmH"/>
            <column name="airport_id" value="53EHfQ52dsQ8h9R7ezwUbZ"/>
            <column name="customer_id" value="1IUe73HCc9Qfjl1sxhasNI"/>
            <column name="type_of_service" value="Airport Assistance With Lounge"/>
            <column name="customer_phone" value="1234567890"/>
            <column name="guest_phone" value="1234567890"/>
            <column name="flight_date" valueDate="2019-06-01T11:00:00"/>
            <column name="flight_code" value="AAA"/>
            <column name="flight_number" value="111"/>
            <column name="number_of_luggages" valueNumeric="2"/>
            <column name="number_of_passengers" valueNumeric="2"/>
            <column name="pickup_address" value="Jl Cendrawish Palmerah Jakarta Barat"/>
            <column name="airport_transfer" valueBoolean="true"/>
            <column name="pickup_time" valueDate="2019-06-01T08:00:00"/>
            <column name="created_by" value="system"/>
            <column name="created_date" valueComputed="CURRENT_TIMESTAMP"/>
        </insert>
        
    </changeSet>
    
    <changeSet author="FLH" id="ass-airport-assistance-data-2">
        
        <insert tableName="ass_arrival">
            <column name="id" value="3K1aI9PFpfTbmlGGfEBaxV"/>
            <column name="airport_id" value="53EHfQ52dsQ8h9R7ezwUbZ"/>
            <column name="customer_id" value="1IUe73HCc9Qfjl1sxhasNI"/>
            <column name="type_of_service" value="Airport Assistance With Lounge"/>
            <column name="customer_phone" value="1234567890"/>
            <column name="flight_date" valueDate="2019-06-01T11:00:00"/>
            <column name="flight_code" value="AAA"/>
            <column name="flight_number" value="111"/>
            <column name="number_of_luggages" valueNumeric="2"/>
            <column name="number_of_passengers" valueNumeric="2"/>
            <column name="drop_off_address" value="Jl Cendrawish Palmerah Jakarta Barat"/>
            <column name="airport_transfer" valueBoolean="true"/>
            <column name="pickup_time" valueDate="2019-06-01T14:00:00"/>
            <column name="created_by" value="system"/>
            <column name="created_date" valueComputed="CURRENT_TIMESTAMP"/>
        </insert>
        
    </changeSet>
    
    <!-- TRAVEL ASSISTANCE -->
    
    <changeSet author="FLH" id="ass-airport-assistance-data-3">
    	
    	<insert tableName="ass_airport_assistance">
            <column name="id" value="1IUe73HCc9Qfjl1sxhasNI"/>
            <column name="total" value="2"/>
            <column name="created_by" value="system"/>
            <column name="created_date" valueComputed="CURRENT_TIMESTAMP"/>
        </insert>
        
        <insert tableName="ass_airport_assistance">
            <column name="id" value="1WUqbiXZnscJsVJD3DVjXy"/>
            <column name="total" value="2"/>
            <column name="created_by" value="system"/>
            <column name="created_date" valueComputed="CURRENT_TIMESTAMP"/>
        </insert>
        
        <insert tableName="ass_airport_assistance">
            <column name="id" value="4dIMucfQGdLNyJPPb3hfv4"/>
            <column name="total" value="2"/>
            <column name="created_by" value="system"/>
            <column name="created_date" valueComputed="CURRENT_TIMESTAMP"/>
        </insert>
        
    </changeSet>
    
</databaseChangeLog>